signalation/__init__.py
signalation/conf/__init__.py
signalation/conf/logger.py
signalation/conf/logging_config.yaml
signalation/conf/settings.py
signalation/entities/__init__.py
signalation/entities/attachment.py
signalation/entities/signal_message.py
signalation/services/__init__.py
signalation/services/producer.py
signalation-1.0.0.dist-info/LICENSE
signalation-1.0.0.dist-info/METADATA
signalation-1.0.0.dist-info/WHEEL
signalation-1.0.0.dist-info/entry_points.txt
signalation-1.0.0.dist-info/top_level.txt
signalation-1.0.0.dist-info/RECORD
