Metadata-Version: 2.1
Name: signalation
Version: 1.0.0
Summary: Produce your messages from your signal account to kafka.
Author-email: Markus Borea <borea17@protonmail.com>
License: MIT License
Project-URL: Homepage, https://github.com/borea17/signal-kafka-producer
Classifier: License :: OSI Approved :: MIT License
Classifier: Programming Language :: Python
Classifier: Programming Language :: Python :: 3
Requires-Python: >=3.10
License-File: LICENSE
Requires-Dist: coloredlogs (==15.0.1)
Requires-Dist: confluent-kafka (==2.0.2)
Requires-Dist: click (==8.1.3)
Requires-Dist: numpy (==1.24.2)
Requires-Dist: pandas (==1.5.3)
Requires-Dist: pydantic (==1.10.5)
Requires-Dist: python-dotenv (==1.0.0)
Requires-Dist: pyyaml (==6.0)
Requires-Dist: requests (==2.28.2)
Provides-Extra: dev
Requires-Dist: black (==22.12.0) ; extra == 'dev'
Requires-Dist: flake8 (==6.0.0) ; extra == 'dev'
Requires-Dist: isort (==5.11.4) ; extra == 'dev'
Requires-Dist: pre-commit (==2.21.0) ; extra == 'dev'
Requires-Dist: pytest (==7.1.0) ; extra == 'dev'
Requires-Dist: pytest-cov (==3.0.0) ; extra == 'dev'
Requires-Dist: pytest-timeout (==2.1.0) ; extra == 'dev'
Requires-Dist: pdbpp (>=0.10.3) ; extra == 'dev'
Requires-Dist: requests-mock (==1.10.0) ; extra == 'dev'
